bronk.py
bronk-3.2.2.dist-info/DESCRIPTION.rst
bronk-3.2.2.dist-info/METADATA
bronk-3.2.2.dist-info/RECORD
bronk-3.2.2.dist-info/WHEEL
bronk-3.2.2.dist-info/dependency_links.txt
bronk-3.2.2.dist-info/metadata.json
bronk-3.2.2.dist-info/top_level.txt
